resilience_toolkit/__about__.py
resilience_toolkit/__init__.py
resilience_toolkit-0.0.2.dist-info/METADATA
resilience_toolkit-0.0.2.dist-info/WHEEL
resilience_toolkit-0.0.2.dist-info/licenses/LICENSE.txt
resilience_toolkit-0.0.2.dist-info/RECORD
