Metadata-Version: 2.3
Name: resilience-toolkit
Version: 0.0.2
Project-URL: Documentation, https://github.com/davidejames/resilience-toolkit#readme
Project-URL: Issues, https://github.com/davidejames/resilience-toolkit/issues
Project-URL: Source, https://github.com/davidejames/resilience-toolkit
Author-email: "David E. James" <david.eugene.james@protonmail.com>
License-Expression: MIT
License-File: LICENSE.txt
Classifier: Development Status :: 4 - Beta
Classifier: Programming Language :: Python
Classifier: Programming Language :: Python :: 3.8
Classifier: Programming Language :: Python :: 3.9
Classifier: Programming Language :: Python :: 3.10
Classifier: Programming Language :: Python :: 3.11
Classifier: Programming Language :: Python :: 3.12
Classifier: Programming Language :: Python :: Implementation :: CPython
Classifier: Programming Language :: Python :: Implementation :: PyPy
Requires-Python: >=3.8
Requires-Dist: circuitbreaker-toolkit
Requires-Dist: retry-toolkit
Requires-Dist: timing-toolkit
